baiji/__init__.py
baiji/serialization/__init__.py
baiji/serialization/csv.py
baiji/serialization/json.py
baiji/serialization/pickle.py
baiji/serialization/test_csv.py
baiji/serialization/test_json.py
baiji/serialization/test_yaml.py
baiji/serialization/yaml.py
baiji/serialization/util/__init__.py
baiji/serialization/util/importlib.py
baiji/serialization/util/openlib.py
metabaiji_serialization-2.2.1.dist-info/LICENSE
metabaiji_serialization-2.2.1.dist-info/METADATA
metabaiji_serialization-2.2.1.dist-info/WHEEL
metabaiji_serialization-2.2.1.dist-info/top_level.txt
metabaiji_serialization-2.2.1.dist-info/RECORD
